jira_easy_api/__init__.py
jira_easy_api/jira_easy_api_core.py
jira_easy_api-0.1.2.dist-info/LICENSE
jira_easy_api-0.1.2.dist-info/METADATA
jira_easy_api-0.1.2.dist-info/WHEEL
jira_easy_api-0.1.2.dist-info/top_level.txt
jira_easy_api-0.1.2.dist-info/RECORD
