Metadata-Version: 2.1
Name: jira-easy-api
Version: 0.1.2
Summary: A wrapper around Jira API to run jira commands missing in their UI as oneliners
Home-page: https://github.com/DovaX/jira_easy_api
Author: DovaX
Author-email: dovax.ai@gmail.com
License: UNKNOWN
Platform: UNKNOWN
Classifier: Programming Language :: Python :: 3
Classifier: License :: OSI Approved :: MIT License
Classifier: Operating System :: OS Independent
Requires-Python: >=3.6
Requires-Dist: jira
